LICENSE
MANIFEST.in
README.md
setup.py
PTTLibrary/PTT.py
PTTLibrary/_api_bucket.py
PTTLibrary/_api_call_status.py
PTTLibrary/_api_get_board_info.py
PTTLibrary/_api_get_board_list.py
PTTLibrary/_api_get_favourite_board.py
PTTLibrary/_api_get_newest_index.py
PTTLibrary/_api_get_post.py
PTTLibrary/_api_get_post_index.py
PTTLibrary/_api_get_time.py
PTTLibrary/_api_get_user.py
PTTLibrary/_api_give_money.py
PTTLibrary/_api_has_new_mail.py
PTTLibrary/_api_loginout.py
PTTLibrary/_api_mail.py
PTTLibrary/_api_mark_post.py
PTTLibrary/_api_post.py
PTTLibrary/_api_push.py
PTTLibrary/_api_reply_post.py
PTTLibrary/_api_search_user.py
PTTLibrary/_api_set_board_title.py
PTTLibrary/_api_waterball.py
PTTLibrary/check_value.py
PTTLibrary/command.py
PTTLibrary/config.py
PTTLibrary/connect_core.py
PTTLibrary/data_type.py
PTTLibrary/exceptions.py
PTTLibrary/i18n.py
PTTLibrary/lib_util.py
PTTLibrary/log.py
PTTLibrary/screens.py
PTTLibrary/version.py
PTTLibrary.egg-info/PKG-INFO
PTTLibrary.egg-info/SOURCES.txt
PTTLibrary.egg-info/dependency_links.txt
PTTLibrary.egg-info/requires.txt
PTTLibrary.egg-info/top_level.txt
PTTlibrary/PTT.py
PTTlibrary/_api_bucket.py
PTTlibrary/_api_call_status.py
PTTlibrary/_api_get_board_info.py
PTTlibrary/_api_get_board_list.py
PTTlibrary/_api_get_favourite_board.py
PTTlibrary/_api_get_newest_index.py
PTTlibrary/_api_get_post.py
PTTlibrary/_api_get_post_index.py
PTTlibrary/_api_get_time.py
PTTlibrary/_api_get_user.py
PTTlibrary/_api_give_money.py
PTTlibrary/_api_has_new_mail.py
PTTlibrary/_api_loginout.py
PTTlibrary/_api_mail.py
PTTlibrary/_api_mark_post.py
PTTlibrary/_api_post.py
PTTlibrary/_api_push.py
PTTlibrary/_api_reply_post.py
PTTlibrary/_api_search_user.py
PTTlibrary/_api_set_board_title.py
PTTlibrary/_api_waterball.py
PTTlibrary/check_value.py
PTTlibrary/command.py
PTTlibrary/config.py
PTTlibrary/connect_core.py
PTTlibrary/data_type.py
PTTlibrary/exceptions.py
PTTlibrary/i18n.py
PTTlibrary/lib_util.py
PTTlibrary/log.py
PTTlibrary/screens.py
PTTlibrary/version.py
PTTlibrary/__pycache__/version.cpython-37.pyc