Metadata-Version: 1.2
Name: PTTLibrary
Version: 0.9.1
Summary: PTT library
Home-page: https://github.com/PttCodingMan/PTTLibrary
Author: CodingMan
Author-email: thetruth0906@gmail.com
License: UNKNOWN
Keywords: PTT,crawler,bot,library
Platform: UNKNOWN
Classifier: Development Status :: 4 - Beta
Classifier: Operating System :: POSIX :: Linux
Classifier: Operating System :: MacOS :: MacOS X
Classifier: Operating System :: Microsoft :: Windows :: Windows 10
Classifier: Intended Audience :: Developers
Classifier: Topic :: Communications :: BBS
Classifier: Topic :: Software Development :: Libraries :: Python Modules
Classifier: Topic :: Internet
Classifier: Topic :: Terminals :: Telnet
Classifier: License :: OSI Approved :: MIT License
Classifier: Programming Language :: Python :: 3.6
Classifier: Programming Language :: Python :: 3.7
Classifier: Natural Language :: Chinese (Traditional)
Classifier: Natural Language :: English
Requires-Python: >=3.6
